django_ex/__init__.py
django_ex/middleware/__init__.py
django_ex/middleware/http.py
django_ex-0.0.7.dist-info/METADATA
django_ex-0.0.7.dist-info/WHEEL
django_ex-0.0.7.dist-info/licenses/LICENSE
django_ex-0.0.7.dist-info/RECORD
